Workbook

Sheet INCOME WITHDRWAL STATE
A1: CASH/BANK INCOME STATE Sep 2026
A2: SER NO. | B2: DATED | C2: PARTICULAR/ DETAIL | D2: IN CASH | E2: IN BANK | F2: TOTAL | G2: IN CASH | J2: IN BANK | O2: TOTAL
G3: CEO | H3: CFO | I3: DIR OPS | J3: CO'S ACCT (ALLIED) | K3: CO'S ACCT (ASKARI) | L3: CFO'S ACCT | M3: CEO ACC | N3: SONERI ACC
A4: BBF | J4: 707902 | K4: 3620818 | L4: -334707 | M4: 55555 | N4: 775855 | R4: -1119514
A5: 1 | B5: 46267 | C5: WUSAT | D5: 264000 | F5: =SUM(D5:E5) -> 264000 | G5: 264000 | O5: =SUM(G5:N5) -> 264000 | R5: PCI/PFM/68HS | T5: =F28+F26+F13 -> 646000
A6: 2 | B6: 46279 | C6: ELYSIUM | E6: 36000 | F6: =SUM(D6:E6) -> 36000 | L6: 36000 | O6: =SUM(G6:N6) -> 36000
A7: 3 | B7: 46275 | C7: EMAAR | E7: 4754162 | F7: =SUM(D7:E7) -> 4754162 | K7: 4754162 | O7: =SUM(G7:N7) -> 4754162 | R7: -1119514
A8: 4 | B8: 46273 | C8: DHA DENTAL LAB | E8: 35000 | F8: =SUM(D8:E8) -> 35000 | K8: 500 | L8: 35000 | O8: =SUM(G8:N8) -> 35500
A9: 5 | B9: 46279 | C9: DEPOSIT FROM ABL | E9: 0 | F9: =SUM(D9:E9) -> 0 | K9: 250000 | O9: =SUM(G9:N9) -> 250000
A10: 6 | B10: 46279 | C10: CASH DEPOSIT FROM ABL IN CFO ACC | F10: =SUM(D10:E10) -> 0 | K10: 0 | L10: 550000 | O10: =SUM(G10:N10) -> 550000
A11: 7 | B11: 46272 | C11: MIU (AJK BANK) | E11: 1246511 | F11: =SUM(D11:E11) -> 1246511 | N11: 1246511 | O11: =SUM(G11:N11) -> 1246511
A12: 8 | B12: 46266 | C12: CBR | E12: =214272*2 -> 428544 | F12: =SUM(D12:E12) -> 428544 | N12: 428544 | O12: =SUM(G12:N12) -> 428544 | R12: =264000-55000 -> 209000
A13: 9 | B13: 46273 | C13: 68 HS | E13: 204000 | F13: =SUM(D13:E13) -> 204000 | L13: 204000 | O13: =SUM(G13:N13) -> 204000 | R13: =R12-157668 -> 51332
A14: 10 | B14: 46287 | C14: KALOON CHEMICALS | D14: 24000 | F14: =SUM(D14:E14) -> 24000 | L14: 24000 | O14: =SUM(G14:N14) -> 24000
A15: 11 | B15: 46286 | C15: HMC TAXILA | E15: 4629379 | F15: =SUM(D15:E15) -> 4629379 | K15: 4629379 | O15: =SUM(G15:N15) -> 4629379
A16: 12 | B16: 46294 | C16: NOVA | D16: 1900000 | F16: =SUM(D16:E16) -> 1900000 | G16: 1900000 | O16: =SUM(G16:N16) -> 1900000
A17: 13 | B17: 46282 | C17: J SONS | E17: 38500 | F17: =SUM(D17:E17) -> 38500 | L17: 38500 | O17: =SUM(G17:N17) -> 38500
A18: 14 | B18: 46287 | C18: MR SALAAR/Gulreiz | F18: =SUM(D18:E18) -> 0 | O18: =SUM(G18:N18) -> 0
A19: 15 | B19: 46266 | C19: RISING SUN LODGES | D19: 90000 | F19: =SUM(D19:E19) -> 90000 | H19: 0 | L19: 90000 | O19: =SUM(G19:N19) -> 90000
A20: 16 | B20: 46273 | C20: PRG | E20: 65340 | F20: =SUM(D20:E20) -> 65340 | L20: 65340 | O20: =SUM(G20:N20) -> 65340
A21: 17 | B21: 46273 | C21: SWEET PALACE | D21: 90000 | F21: =SUM(D21:E21) -> 90000 | G21: 90000 | O21: =SUM(G21:N21) -> 90000
A22: 18 | B22: 46272 | C22: AWT | E22: 148000 | F22: =SUM(D22:E22) -> 148000 | L22: 148000 | O22: =SUM(G22:N22) -> 148000
A23: 19 | B23: 46275 | C23: DOLMEN | E23: 510152 | F23: =SUM(D23:E23) -> 510152 | J23: 510152 | O23: =SUM(G23:N23) -> 510152
A24: 20 | B24: 46269 | C24: SGC SERVICES | E24: 68752 | F24: =SUM(D24:E24) -> 68752 | J24: 68752 | O24: =SUM(G24:N24) -> 68752
A25: 21 | B25: 46269 | C25: SGC THALIAN | E25: 745927 | F25: =SUM(D25:E25) -> 745927 | J25: 745927 | O25: =SUM(G25:N25) -> 745927
A26: 22 | B26: 46286 | C26: PFM | D26: 238000 | F26: =SUM(D26:E26) -> 238000 | L26: 238000 | O26: =SUM(G26:N26) -> 238000
A27: 23 | B27: 46286 | C27: ALI SADAAT (MANDWAL, CHAKRI) | E27: 216000 | F27: =SUM(D27:E27) -> 216000 | L27: 216000 | O27: =SUM(G27:N27) -> 216000
A28: 24 | B28: 46279 | C28: PCI | D28: 204000 | F28: =SUM(D28:E28) -> 204000 | G28: 0 | L28: 204000 | O28: =SUM(G28:N28) -> 204000
A29: 25 | B29: 46277 | C29: LEXUS | E29: 160000 | F29: =SUM(D29:E29) -> 160000 | M29: 160000 | O29: =SUM(G29:N29) -> 160000
A30: 26 | B30: 46295 | C30: CBU TAXILA | E30: 0 | F30: =SUM(D30:E30) -> 0 | J30: 0 | K30: 0 | O30: =SUM(G30:N30) -> 0
A31: 27 | B31: 46280 | C31: RECEIVED FROM ABL ACC | F31: =SUM(D31:E31) -> 0 | K31: 0 | O31: =SUM(G31:N31) -> 0
A32: 28 | B32: 46269 | C32: INNOVATIVE | E32: 64342 | F32: =SUM(D32:E32) -> 64342 | N32: 64342 | O32: =SUM(G32:N32) -> 64342
A33: 29 | C33: Inkling School | D33: 38000 | F33: =SUM(D33:E33) -> 38000 | G33: 0 | H33: 0 | L33: 38000 | O33: =SUM(G33:N33) -> 38000
A34: 30 | B34: 46274 | C34: TIGES | E34: =47800*3 -> 143400 | F34: =SUM(D34:E34) -> 143400 | J34: 47800 | K34: =47800*2 -> 95600 | O34: =SUM(G34:N34) -> 143400
A35: 31 | B35: 46273 | C35: Bin Zahid | E35: 36000 | F35: =SUM(D35:E35) -> 36000 | L35: 36000 | O35: =SUM(G35:N35) -> 36000
A36: TOTAL | D36: =SUM(D4:D35) -> 2848000 | E36: =SUM(E4:E35) -> 13530009 | F36: =SUM(F4:F35) -> 16378009 | G36: =SUM(G4:G35) -> 2254000 | H36: =SUM(H4:H35) -> 0 | O36: =SUM(G36:N36) -> 2254000
A37: TRANSFER INTER BANK | J37: =SUM(J4:J36) -> 2080533 | K37: =SUM(K4:K36) -> 13350459 | L37: =SUM(L4:L36) -> 1588133 | M37: =SUM(M4:M36) -> 215555 | N37: =SUM(N4:N36) -> 2515252
G38: =SUM(G36:G37) -> 2254000 | H38: =SUM(H36:H37) -> 0 | I38: =SUM(I36:I37) -> 0 | J38: =SUM(J36:J37) -> 2080533 | K38: =SUM(K36:K37) -> 13350459 | L38: =SUM(L36:L37) -> 1588133 | M38: =SUM(M36:M37) -> 215555 | N38: =SUM(N36:N37) -> 2515252
Q39: RECEIPT IN OFFICE
A40: CASH/BANK WITHDRAWAL STATE SEP 2026 | Q40: CASH | R40: CHEQUE | S40: TOTAL
A41: SER NO. | B41: DATED | C41: PARTICULAR/ DETAIL | D41: FROM CASH | E41: FROM BANK | F41: TOTAL | G41: FROM CASH | J41: IN BANK | O41: TOTAL | Q41: BBF
G42: CEO | H42: CFO | I42: DIR OPS | J42: CO'S ACCT (ALLIED) | K42: CO'S ACCT (ASKARI) | L42: CFO'S ACCT | M42: CEO ACC | N42: SONERI ACC | S42: =SUM(Q42:R42) -> 0
F43: =SUM(D43:E43) -> 0 | O43: =SUM(G43:L43) -> 0 | S43: =SUM(Q43:R43) -> 0
A44: 1 | B44: 46267 | C44: PETTY CASH REIMBURSED | E44: 5000 | F44: =SUM(D44:E44) -> 5000 | H44: 0 | L44: 5000 | O44: =SUM(G44:N44) -> 5000 | S44: =SUM(Q44:R44) -> 0
A45: 2 | B45: 46267 | C45: SALARY OF RISING SUN 2X GD | E45: 80000 | F45: =SUM(D45:E45) -> 80000 | H45: 0 | L45: 80000 | O45: =SUM(G45:N45) -> 80000 | R45: 80000 | S45: =SUM(Q45:R45) -> 80000
A46: 3 | B46: 46267 | C46: WEAPON PURCHASED | E46: 15000 | F46: =SUM(D46:E46) -> 15000 | L46: 15000 | O46: =SUM(G46:N46) -> 15000 | R46: 15000 | S46: =SUM(Q46:R46) -> 15000
A47: 4 | B47: 46268 | C47: INSURANCE PAID FOR GUARDS 6 months | E47: 281563 | F47: =SUM(D47:E47) -> 281563 | J47: 281563 | O47: =SUM(G47:N47) -> 281563 | R47: 281563 | S47: =SUM(Q47:R47) -> 281563
A48: 5 | B48: 46267 | C48: PTA LICENSE RENEWAL FEES | E48: 180000 | F48: =SUM(D48:E48) -> 180000 | J48: 180000 | O48: =SUM(G48:N48) -> 180000 | R48: 180000 | S48: =SUM(Q48:R48) -> 180000
A49: 6 | B49: 46270 | C49: SALARY OF 53X EMAAR GDS | E49: 2814598 | F49: =SUM(D49:E49) -> 2814598 | K49: 2814598 | O49: =SUM(G49:N49) -> 2814598 | R49: 2814598 | S49: =SUM(Q49:R49) -> 2814598
A50: 7 | B50: 46270 | C50: SALARY OF 13X EMAAR GDS | E50: 706601 | F50: =SUM(D50:E50) -> 706601 | K50: 706601 | O50: =SUM(G50:N50) -> 706601 | R50: 706601 | S50: =SUM(Q50:R50) -> 706601
A51: 8 | B51: 46270 | C51: SALARY OF 1X INKLING GUARD | E51: 28000 | F51: =SUM(D51:E51) -> 28000 | L51: 28000 | O51: =SUM(G51:N51) -> 28000 | R51: 28000 | S51: =SUM(Q51:R51) -> 28000
A52: 9 | B52: 46273 | C52: SALARY 2X GDS SWEET PALACE | E52: 64000 | F52: =SUM(D52:E52) -> 64000 | L52: 64000 | O52: =SUM(G52:N52) -> 64000 | R52: 64000 | S52: =SUM(Q52:R52) -> 64000 | V52: =S45+S50+S51+S52+S53+S55+S56+S57+S58+S59 -> 1179348
A53: 10 | B53: 46273 | C53: SALARY OF 1X J SONS GD | E53: 24000 | F53: =SUM(D53:E53) -> 24000 | L53: 24000 | O53: =SUM(G53:N53) -> 24000 | R53: 24000 | S53: =SUM(Q53:R53) -> 24000
A54: 11 | B54: 46270 | C54: SALARY OF NOVA GD AUG AND SEP CLEARED NASEEM AWAN | D54: 47000 | F54: =SUM(D54:E54) -> 47000 | G54: 0 | H54: 0 | L54: 47000 | O54: =SUM(G54:N54) -> 47000 | R54: 47000 | S54: =SUM(Q54:R54) -> 47000
A55: 12 | B55: 46269 | C55: BANK TRANSFER FOR AJK EXPENSES | E55: 24200 | F55: =SUM(D55:E55) -> 24200 | L55: 24200 | O55: =SUM(G55:N55) -> 24200 | S55: =SUM(Q55:R55) -> 0
A56: 13 | B56: 46274 | C56: SALARY OF RELEIVER RIAZ | E56: 25000 | F56: =SUM(D56:E56) -> 25000 | L56: 25000 | O56: =SUM(G56:N56) -> 25000 | R56: 25000 | S56: =SUM(Q56:R56) -> 25000
A57: 14 | B57: 46272 | C57: SALARY OF GUL REHMAN | D57: 55000 | F57: =SUM(D57:E57) -> 55000 | G57: 55000 | O57: =SUM(G57:N57) -> 55000 | Q57: 55000 | S57: =SUM(Q57:R57) -> 55000
A58: 15 | B58: 46275 | C58: SALARY OF MIU CAMP OFFICE | E58: 35000 | F58: =SUM(D58:E58) -> 35000 | N58: 35000 | O58: =SUM(G58:N58) -> 35000 | R58: 35000 | S58: =SUM(Q58:R58) -> 35000
A59: 16 | B59: 46275 | C59: SALARY OF 5X WUSAT GUARDS | E59: 161747 | F59: =SUM(D59:E59) -> 161747 | L59: 161747 | O59: =SUM(G59:N59) -> 161747 | R59: 161747 | S59: =SUM(Q59:R59) -> 161747
A60: 17 | B60: 46275 | C60: SALARY OF DHA DENTAL GUARD | E60: 28000 | F60: =SUM(D60:E60) -> 28000 | L60: 28000 | O60: =SUM(G60:N60) -> 28000 | R60: 28000 | S60: =SUM(Q60:R60) -> 28000
A61: 18 | B61: 46275 | C61: SALARY OF 4X AWT GUARDS | E61: 91419 | F61: =SUM(D61:E61) -> 91419 | L61: 91419 | O61: =SUM(G61:N61) -> 91419 | R61: 91419 | S61: =SUM(Q61:R61) -> 91419
A62: 19 | B62: 46275 | C62: AJK EXP | E62: 5000 | F62: =SUM(D62:E62) -> 5000 | L62: 5000 | O62: =SUM(G62:N62) -> 5000 | S62: =SUM(Q62:R62) -> 0 | V62: 60500
A63: 20 | B63: 46275 | C63: SALARY OF 6X DOLMEN GDS | E63: 223000 | F63: =SUM(D63:E63) -> 223000 | K63: 223000 | O63: =SUM(G63:N63) -> 223000 | R63: 223000 | S63: =SUM(Q63:R63) -> 223000
A64: 21 | B64: 46275 | C64: SALARY OF LEXUS AND MIMC | E64: 899000 | F64: =SUM(D64:E64) -> 899000 | N64: 899000 | O64: =SUM(G64:N64) -> 899000 | R64: 899000 | S64: =SUM(Q64:R64) -> 899000
A65: 22 | B65: 46276 | C65: CHEQUE FOR MIU SAL AND RENT? | E65: 350000 | F65: =SUM(D65:E65) -> 350000 | J65: 350000 | L65: 4000 | O65: =SUM(G65:N65) -> 354000 | R65: 354000 | S65: =SUM(Q65:R65) -> 354000 | V65: =258+96 -> 354
A66: 23 | B66: 46276 | C66: SALARY OF 5X OFFICE STAFF | E66: 270000 | F66: =SUM(D66:E66) -> 270000 | K66: 270000 | O66: =SUM(G66:N66) -> 270000 | R66: 270000 | S66: =SUM(Q66:R66) -> 270000
A67: 24 | B67: 46276 | C67: SALARY OF 3X DOLMEN GDS | E67: 111000 | F67: =SUM(D67:E67) -> 111000 | K67: 111000 | O67: =SUM(G67:N67) -> 111000 | R67: 111000 | S67: =SUM(Q67:R67) -> 111000
A68: 25 | B68: 46276 | C68: SALARY OF 1X WUSAT GD | E68: 6307 | F68: =SUM(D68:E68) -> 6307 | K68: 6307 | O68: =SUM(G68:N68) -> 6307 | R68: 6307 | S68: =SUM(Q68:R68) -> 6307
A69: 26 | B69: 46276 | C69: SALARY OF 4X EMAAR GDS | E69: 159064 | F69: =SUM(D69:E69) -> 159064 | K69: 159064 | O69: =SUM(G69:N69) -> 159064 | R69: 159064 | S69: =SUM(Q69:R69) -> 159064
A70: 27 | B70: 46276 | C70: SALARY OF 1X WUSAT GD | E70: 33030 | F70: =SUM(D70:E70) -> 33030 | K70: 33030 | O70: =SUM(G70:N70) -> 33030 | R70: 33030 | S70: =SUM(Q70:R70) -> 33030
A71: 28 | B71: 46276 | C71: EXCESS 5K FOR ZAMEER SHB BAL PAY AND 4K EXCESS FROM SONERI CHEQUE | E71: 9000 | F71: =SUM(D71:E71) -> 9000 | K71: 9000 | O71: =SUM(G71:N71) -> 9000 | R71: 9000 | S71: =SUM(Q71:R71) -> 9000
A72: 29 | B72: 46276 | C72: SAFDAR CAMBRIDGE SALARY | E72: 10452 | F72: =SUM(D72:E72) -> 10452 | L72: 10452 | O72: =SUM(G72:N72) -> 10452 | R72: 10452 | S72: =SUM(Q72:R72) -> 10452
A73: 30 | B73: 46276 | C73: SALARY OF 103X SALARY OF HMC GUARDS | E73: 3999775 | F73: =SUM(D73:E73) -> 3999775 | K73: 3999775 | O73: =SUM(G73:N73) -> 3999775 | R73: 3999775 | S73: =SUM(Q73:R73) -> 3999775
A74: 32 | B74: 46279 | C74: TRANSFERRED TO AKBL | E74: 250000 | F74: =SUM(D74:E74) -> 250000 | J74: 250000 | O74: =SUM(G74:N74) -> 250000 | S74: =SUM(Q74:R74) -> 0
A75: 33 | B75: 46279 | C75: CHEQUE ISSUED TRANSFERRED TO CFO | E75: 550000 | F75: =SUM(D75:E75) -> 550000 | J75: 550000 | O75: =SUM(G75:N75) -> 550000 | S75: =SUM(Q75:R75) -> 0 | V75: from 550k
A76: 34 | B76: 46279 | C76: SALARIES OF PCI | E76: 530548 | F76: =SUM(D76:E76) -> 530548 | L76: 530548 | O76: =SUM(G76:N76) -> 530548 | R76: 530548 | S76: =SUM(Q76:R76) -> 530548 | V76: pci sal | W76: 530548 | Y76: =550000-W76 -> 19452
A77: 35 | B77: 46279 | C77: CAMBRIDGE SCHOOL 1X GD SALARY | E77: 16500 | F77: =SUM(D77:E77) -> 16500 | L77: 16500 | O77: =SUM(G77:N77) -> 16500 | R77: 16500 | S77: =SUM(Q77:R77) -> 16500 | V77: EOBI | W77: 19452
A78: 36 | B78: 46279 | C78: EOBI | E78: 266500 | F78: =SUM(D78:E78) -> 266500 | L78: 266500 | O78: =SUM(G78:N78) -> 266500 | R78: 266500 | S78: =SUM(Q78:R78) -> 266500 | W78: =G76-W77 -> -19452
A79: 37 | B79: 46279 | C79: CASH WITHDRAWEL | E79: 1000000 | F79: =SUM(D79:E79) -> 1000000 | N79: 1000000 | O79: =SUM(G79:N79) -> 1000000 | S79: =SUM(Q79:R79) -> 0
A80: 38 | B80: 46279 | C80: PETTY CASH REIMBURSED | E80: 8000 | F80: =SUM(D80:E80) -> 8000 | L80: 8000 | O80: =SUM(G80:N80) -> 8000 | S80: =SUM(Q80:R80) -> 0
A81: 39 | B81: 46280 | C81: PRA SALES TAX PAID | E81: 15346 | F81: =SUM(D81:E81) -> 15346 | L81: 15346 | O81: =SUM(G81:N81) -> 15346 | R81: 15346 | S81: =SUM(Q81:R81) -> 15346
A82: 40 | B82: 46280 | C82: FBR SALES TAX PAID | E82: 41923 | F82: =SUM(D82:E82) -> 41923 | L82: 41923 | O82: =SUM(G82:N82) -> 41923 | R82: 41923 | S82: =SUM(Q82:R82) -> 41923 | V82: CASH RECEIVED TODAY | Y82: =550000+204000 -> 754000
A83: 41 | B83: 46280 | C83: TRANSFERRED TO AKBL | E83: 0 | F83: =SUM(D83:E83) -> 0 | J83: 0 | O83: =SUM(G83:N83) -> 0 | S83: =SUM(Q83:R83) -> 0 | V83: PCI SALARIES | Y83: =-398548-25000 -> -423548
A84: 42 | B84: 46283 | C84: SALARY OF NOVA ISB GD USMAN HAIDER | E84: 25000 | F84: =SUM(D84:E84) -> 25000 | L84: 25000 | O84: =SUM(G84:N84) -> 25000 | R84: 25000 | S84: =SUM(Q84:R84) -> 25000 | V84: CAMBRIDGE SALARIES | Y84: -16500
A85: 43 | B85: 46283 | C85: SADQA | E85: 5000 | F85: =SUM(D85:E85) -> 5000 | L85: 5000 | O85: =SUM(G85:N85) -> 5000 | R85: 5000 | S85: =SUM(Q85:R85) -> 5000 | V85: EOBI | Y85: -266500
A86: 44 | B86: 46286 | C86: PRG SALARIES | E86: 49000 | F86: =SUM(D86:E86) -> 49000 | L86: 49000 | O86: =SUM(G86:N86) -> 49000 | R86: 49000 | S86: =SUM(Q86:R86) -> 49000 | Y86: =SUM(Y82:Y85) -> 47452
A87: 45 | B87: 46286 | C87: MANDWAAL SALARIES | E87: 50000 | F87: =SUM(D87:E87) -> 50000 | L87: 50000 | O87: =SUM(G87:N87) -> 50000 | R87: 50000 | S87: =SUM(Q87:R87) -> 50000
A88: 46 | B88: 46286 | C88: EMAAR FOOD BILL | E88: 227585 | F88: =SUM(D88:E88) -> 227585 | L88: 227585 | O88: =SUM(G88:N88) -> 227585 | R88: 227585 | S88: =SUM(Q88:R88) -> 227585
A89: 47 | B89: 46283 | C89: ADVANCE TO MURSALEEN KHAN NOVA CHD | E89: 10000 | F89: =SUM(D89:E89) -> 10000 | M89: 10000 | O89: =SUM(G89:N89) -> 10000 | R89: 10000 | S89: =SUM(Q89:R89) -> 10000
A90: 48 | B90: 46267 | C90: CASH WITHDRAWEL | E90: 81960 | F90: =SUM(D90:E90) -> 81960 | J90: 81960 | O90: =SUM(G90:N90) -> 81960 | S90: =SUM(Q90:R90) -> 0
A91: 49 | B91: 46286 | C91: FED DEDUCTIONS AND SERVICE CHARGES | E91: 3135 | F91: =SUM(D91:E91) -> 3135 | J91: =387010-383875 -> 3135 | O91: =SUM(G91:N91) -> 3135 | R91: 3135 | S91: =SUM(Q91:R91) -> 3135
A92: 50 | B92: 46283 | C92: SALARY OF 6X HMC GUARDS SALARY | E92: 237600 | F92: =SUM(D92:E92) -> 237600 | K92: 237600 | O92: =SUM(G92:N92) -> 237600 | R92: 237600 | S92: =SUM(Q92:R92) -> 237600
A93: 51 | B93: 46283 | C93: SALARY OF BISMILLAH JAN NOVA PSH | E93: 26000 | F93: =SUM(D93:E93) -> 26000 | K93: 26000 | O93: =SUM(G93:N93) -> 26000 | R93: 26000 | S93: =SUM(Q93:R93) -> 26000
A94: 52 | B94: 46287 | C94: SALARY OF 2X HMC GUARDS | E94: 57587 | F94: =SUM(D94:E94) -> 57587 | K94: 57587 | O94: =SUM(G94:N94) -> 57587 | R94: 57587 | S94: =SUM(Q94:R94) -> 57587
A95: 53 | B95: 46287 | C95: SADQA 3x | E95: 10000 | F95: =SUM(D95:E95) -> 10000 | K95: 10000 | O95: =SUM(G95:N95) -> 10000 | R95: 10000 | S95: =SUM(Q95:R95) -> 10000
A96: 54 | B96: 46282 | C96: ADVANCE TO NASIR ALI SGC THALIAN GUARD | E96: 5000 | F96: =SUM(D96:E96) -> 5000 | L96: 5000 | O96: =SUM(G96:N96) -> 5000 | R96: 5000 | S96: =SUM(Q96:R96) -> 5000
A97: 55 | B97: 46287 | C97: STATIONARY BILL FTM AUG 26 | E97: 3300 | F97: =SUM(D97:E97) -> 3300 | K97: 3300 | O97: =SUM(G97:N97) -> 3300 | R97: 3300 | S97: =SUM(Q97:R97) -> 3300
A98: 56 | B98: 46287 | C98: EMAAR ACCOMODATION RENT | E98: 60500 | F98: =SUM(D98:E98) -> 60500 | K98: 60500 | O98: =SUM(G98:N98) -> 60500 | R98: 60500 | S98: =SUM(Q98:R98) -> 60500
A99: 57 | B99: 46287 | C99: TEA BILL | E99: 5180 | F99: =SUM(D99:E99) -> 5180 | K99: 5180 | O99: =SUM(G99:N99) -> 5180 | R99: 5180 | S99: =SUM(Q99:R99) -> 5180
A100: 58 | B100: 46287 | C100: SGC SALARIES | E100: 467258 | F100: =SUM(D100:E100) -> 467258 | K100: 467258 | O100: =SUM(G100:N100) -> 467258 | R100: 467258 | S100: =SUM(Q100:R100) -> 467258
...

Sheet SUMMARY PAY EXPENSE SHEET
A1: EXPENSE SHEET SUMMARY FTM SEP 2026
A2: SER NO. | B2: EXPENSE TYPE | C2: EMAAR | D2: TIGES SGC | E2: WUSAT | F2: NOVA ISB | G2: NOVA QTBL | H2: NOVA PSH | I2: NOVA CSD | J2: PREMIER SALES | K2: PCI/PFM/68 | L2: SGC-THALIAN | M2: PRG | N2: MANDWAL | O2: J SONS | P2: HMC/CBU | Q2: KALOON | R2: ELYSIUM | S2: DHA DENTAL CENTRE | T2: CBR | U2: DOLMEN | V2: SWEET PALACE | W2: RELEIVERS | X2: INKLING | Y2: AWT | Z2: MIU/MOMT | AA2: MR SALAAR | AB2: RISING SUN | AC2: OFFICE | AD2: TOTAL
A3: 1 | B3: SALARIES PAID | C3: ='EXPENSE SHEET'!H50 -> 3680263 | D3: ='EXPENSE SHEET'!I50 -> 0 | E3: ='EXPENSE SHEET'!J50 -> 39337 | F3: ='EXPENSE SHEET'!K50 -> 543129 | G3: ='EXPENSE SHEET'!L50 -> 100000 | H3: ='EXPENSE SHEET'!M50 -> 196000 | I3: ='EXPENSE SHEET'!N50 -> 322000 | J3: ='EXPENSE SHEET'!O50 -> 0 | ... AC3: ='EXPENSE SHEET'!AH50 -> 1503747 | AD3: =SUM(C3:AC3) -> 12680663
A4: 2 | B4: TOTAL ADVANCE PAYMENT | C4: ='EXPENSE SHEET'!H77 -> 5000 | D4: ='EXPENSE SHEET'!I77 -> 0 | E4: ='EXPENSE SHEET'!J77 -> 0 | F4: ='EXPENSE SHEET'!K77 -> 0 | G4: ='EXPENSE SHEET'!L77 -> 0 | H4: ='EXPENSE SHEET'!M77 -> 0 | I4: ='EXPENSE SHEET'!N77 -> 10000 | J4: ='EXPENSE SHEET'!O77 -> 0 | ... AC4: ='EXPENSE SHEET'!AH77 -> 0 | AD4: =SUM(C4:AC4) -> 30000
A5: 3 | B5: EXPENSE INCURRED ON SALARIES DISTRIBUTION | C5: ='EXPENSE SHEET'!H79 -> 0 | D5: ='EXPENSE SHEET'!I79 -> 0 | E5: ='EXPENSE SHEET'!J79 -> 0 | F5: ='EXPENSE SHEET'!K79 -> 0 | G5: ='EXPENSE SHEET'!L79 -> 0 | H5: ='EXPENSE SHEET'!M79 -> 0 | I5: ='EXPENSE SHEET'!N79 -> 0 | J5: ='EXPENSE SHEET'!O79 -> 0 | ... V5: ='EXPENSE SHEET'!AA79 -> 0 | W5: ='EXPENSE SHEET'!AB52 -> 0 | X5: ='EXPENSE SHEET'!AC52 -> 0 | Y5: ='EXPENSE SHEET'!AD52 -> 0 | Z5: ='EXPENSE SHEET'!AE52 -> 0 | AA5: ='EXPENSE SHEET'!AF79 -> 0 | AB5: ='EXPENSE SHEET'!AG79 -> 0 | AC5: ='EXPENSE SHEET'!AH79 -> 0 | AD5: =SUM(C5:AC5) -> 0
A6: 4 | B6: TOTAL TRAVEL EXPENSE | C6: ='EXPENSE SHEET'!H140 -> 220 | D6: ='EXPENSE SHEET'!I140 -> 0 | E6: ='EXPENSE SHEET'!J140 -> 0 | F6: ='EXPENSE SHEET'!K140 -> 0 | G6: ='EXPENSE SHEET'!L140 -> 0 | H6: ='EXPENSE SHEET'!M140 -> 0 | I6: ='EXPENSE SHEET'!N140 -> 0 | J6: ='EXPENSE SHEET'!O140 -> 0 | ... AC6: ='EXPENSE SHEET'!AH140 -> 90773 | AD6: =SUM(C6:AC6) -> 94151
A7: 5 | B7: TOTAL FOOD EXPENSE | C7: ='EXPENSE SHEET'!H156 -> 0 | D7: ='EXPENSE SHEET'!I156 -> 0 | E7: ='EXPENSE SHEET'!J156 -> 0 | F7: ='EXPENSE SHEET'!K156 -> 0 | G7: ='EXPENSE SHEET'!L156 -> 0 | H7: ='EXPENSE SHEET'!M156 -> 0 | I7: ='EXPENSE SHEET'!N156 -> 0 | J7: ='EXPENSE SHEET'!O156 -> 0 | ... AC7: ='EXPENSE SHEET'!AH156 -> 9330 | AD7: =SUM(C7:AC7) -> 10830
A8: 6 | B8: TOTAL TEABREAK EXPENSE | C8: ='EXPENSE SHEET'!H160 -> 0 | D8: ='EXPENSE SHEET'!I160 -> 0 | E8: ='EXPENSE SHEET'!J160 -> 0 | F8: ='EXPENSE SHEET'!K160 -> 0 | G8: ='EXPENSE SHEET'!L160 -> 0 | H8: ='EXPENSE SHEET'!M160 -> 0 | I8: ='EXPENSE SHEET'!N160 -> 0 | J8: ='EXPENSE SHEET'!O160 -> 0 | ... AC8: ='EXPENSE SHEET'!AH160 -> 7680 | AD8: =SUM(C8:AC8) -> 7680
A9: 7 | B9: TOTAL STATIONERY EXPENSE | C9: ='EXPENSE SHEET'!H164 -> 0 | D9: ='EXPENSE SHEET'!I164 -> 0 | E9: ='EXPENSE SHEET'!J164 -> 0 | F9: ='EXPENSE SHEET'!K164 -> 0 | G9: ='EXPENSE SHEET'!L164 -> 0 | H9: ='EXPENSE SHEET'!M164 -> 0 | I9: ='EXPENSE SHEET'!N164 -> 0 | J9: ='EXPENSE SHEET'!O164 -> 0 | ... AC9: ='EXPENSE SHEET'!AH164 -> 0 | AD9: =SUM(C9:AC9) -> 0
A10: 8 | B10: TOTAL RENT UTILITIES & INTERNET EXPENSE | C10: ='EXPENSE SHEET'!H176 -> 0 | D10: ='EXPENSE SHEET'!I176 -> 0 | E10: ='EXPENSE SHEET'!J176 -> 0 | F10: ='EXPENSE SHEET'!K176 -> 0 | G10: ='EXPENSE SHEET'!L176 -> 0 | H10: ='EXPENSE SHEET'!M176 -> 0 | I10: ='EXPENSE SHEET'!N176 -> 0 | J10: ='EXPENSE SHEET'!O176 -> 0 | ... AC10: ='EXPENSE SHEET'!AH176 -> 657745 | AD10: =SUM(C10:AC10) -> 657745
A11: 9 | B11: TOTAL INVENTORY EXPENSE | C11: ='EXPENSE SHEET'!H184 -> 0 | D11: ='EXPENSE SHEET'!I184 -> 0 | E11: ='EXPENSE SHEET'!J184 -> 0 | F11: ='EXPENSE SHEET'!K184 -> 0 | G11: ='EXPENSE SHEET'!L184 -> 0 | H11: ='EXPENSE SHEET'!M184 -> 0 | I11: ='EXPENSE SHEET'!N184 -> 0 | J11: ='EXPENSE SHEET'!O184 -> 0 | ... AC11: ='EXPENSE SHEET'!AH184 -> 292750 | AD11: =SUM(C11:AC11) -> 292750
A12: 10 | B12: TOTAL LEGAL EXPENSE | C12: ='EXPENSE SHEET'!H191 -> 0 | D12: ='EXPENSE SHEET'!I191 -> 0 | E12: ='EXPENSE SHEET'!J191 -> 0 | F12: ='EXPENSE SHEET'!K191 -> 0 | G12: ='EXPENSE SHEET'!L191 -> 0 | H12: ='EXPENSE SHEET'!M191 -> 0 | I12: ='EXPENSE SHEET'!N191 -> 0 | J12: ='EXPENSE SHEET'!O191 -> 0 | ... AC12: ='EXPENSE SHEET'!AH191 -> 237269 | AD12: =SUM(C12:AC12) -> 518832
A13: 13 | B13: TOTAL MISCELLENIOUS EXPENSE | C13: ='EXPENSE SHEET'!H227 -> 0 | D13: ='EXPENSE SHEET'!I227 -> 0 | E13: ='EXPENSE SHEET'!J227 -> 0 | F13: ='EXPENSE SHEET'!K227 -> 0 | G13: ='EXPENSE SHEET'!L227 -> 0 | H13: ='EXPENSE SHEET'!M227 -> 0 | I13: ='EXPENSE SHEET'!N227 -> 0 | J13: ='EXPENSE SHEET'!O227 -> 0 | ... AC13: ='EXPENSE SHEET'!AH227 -> 50500 | AD13: =SUM(C13:AC13) -> 96902
A14: 12 | B14: TOTAL DRAWINGS BY CEO / CFO | C14: ='EXPENSE SHEET'!H234 -> 0 | D14: ='EXPENSE SHEET'!I234 -> 0 | E14: ='EXPENSE SHEET'!J234 -> 0 | F14: ='EXPENSE SHEET'!K234 -> 0 | G14: ='EXPENSE SHEET'!L234 -> 0 | H14: ='EXPENSE SHEET'!M234 -> 0 | I14: ='EXPENSE SHEET'!N234 -> 0 | J14: ='EXPENSE SHEET'!O234 -> 0 | ... AC14: ='EXPENSE SHEET'!AH234 -> 197410 | AD14: =SUM(C14:AC14) -> 197410
A15: GRAND TOTAL | C15: =SUM(C3:C14) -> 3685483 | D15: =SUM(D3:D14) -> 0 | E15: =SUM(E3:E14) -> 39337 | F15: =SUM(F3:F14) -> 543129 | G15: =SUM(G3:G14) -> 100000 | H15: =SUM(H3:H14) -> 196000 | I15: =SUM(I3:I14) -> 332000 | J15: =SUM(J3:J14) -> 0 | ... AD15: =SUM(AD3:AD14) -> 14586963
A17: PROFIT PER PROJECT
B18: INCOME RECEIVED | C18: ='INCOME WITHDRWAL STATE'!O7 -> 4754162 | D18: ='INCOME WITHDRWAL STATE'!F34 -> 143400 | E18: ='INCOME WITHDRWAL STATE'!O5 -> 264000 | F18: 0 | K18: ='INCOME WITHDRWAL STATE'!T5 -> 646000 | L18: ='INCOME WITHDRWAL STATE'!O25 -> 745927 | M18: ='INCOME WITHDRWAL STATE'!O20 -> 65340 | N18: ='INCOME WITHDRWAL STATE'!O27 -> 216000 | O18: ='INCOME WITHDRWAL STATE'!O17 -> 38500 | P18: ='INCOME WITHDRWAL STATE'!F15+'INCOME WITHDRWAL STATE'!F30 -> 4629379 | Q18: ='INCOME WITHDRWAL STATE'!O14 -> 24000 | R18: ='INCOME WITHDRWAL STATE'!O6 -> 36000 | S18: ='INCOME WITHDRWAL STATE'!O8 -> 35500 | T18: ='INCOME WITHDRWAL STATE'!F12 -> 428544 | U18: ='INCOME WITHDRWAL STATE'!F23 -> 510152 | V18: ='INCOME WITHDRWAL STATE'!O21 -> 90000 | W18: 0 | X18: ='INCOME WITHDRWAL STATE'!O33 -> 38000 | Y18: ='INCOME WITHDRWAL STATE'!O22 -> 148000 | Z18: ='INCOME WITHDRWAL STATE'!F11 -> 1246511 | AB18: ='INCOME WITHDRWAL STATE'!F19 -> 90000 | AC18: 0 | AD18: =SUM(C18:AC18) -> 14149415
B19: PROFIT | C19: =C18-C15 -> 1068679 | D19: =D18-D15 -> 143400 | E19: =E18-E15 -> 224663 | F19: =F18-F15 -> -543129 | G19: =G18-G15 -> -100000 | H19: =H18-H15 -> -196000 | I19: =I18-I15 -> -332000 | J19: =J18-J15 -> 0 | ... AC19: =AC18-AC15 -> -3047204 | AD19: =SUM(C19:AC19) -> -437548

Sheet EXPENSE SHEET
A1: EXPENSE SHEET SUMMARY FTM SEP 2026
A2: SER NO. | B2: EXPENSE TYPE | C2: EXPENSE SUB - TYPE | D2: ENTRY NO. | E2: DATE | F2: DETAIL/PARTICULAR | G2: EXPENDED/DISTRIBUTED BY | H2: EMAAR | I2: TIGES SGC | J2: WUSAT | K2: NOVA ISB | L2: NOVA QTBL | M2: NOVA PSH | N2: NOVA CSD | O2: PREMIER SALES | P2: PCI | Q2: SGC-THALIAN | R2: PRG | S2: MANDWAL | T2: J SONS | U2: HMC | V2: FREELINE | W2: LEXUS | X2: DHA DENTAL CENTRE | Y2: CBR | Z2: DOLMEN | AA2: SWEET PALACE | AB2: RELEIVERS | AC2: INKLING | AD2: AWT | AE2: MIU/MOMT | AF2: MR SALAAR | AG2: RISING SUN | AH2: OFFICE | AI2: TOTAL | AJ2: REMARKS
A3: 1 | B3: SALARY | C3: PAY | E3: 46267 | F3: SALARY OF RISING SUN 2X GD | AG3: 80000 | AH3: 0 | AI3: =SUM(H3:AH3) -> 80000
A4: 2 | B4: SALARY | C4: PAY | E4: 46270 | F4: SALARY OF 53X EMAAR GDS | H4: 2814598 | AH4: 0 | AI4: =SUM(H4:AH4) -> 2814598
A5: 3 | B5: SALARY | C5: PAY | E5: 46270 | F5: SALARY OF 13X EMAAR GDS | H5: 706601 | AH5: 0 | AI5: =SUM(H5:AH5) -> 706601
A6: 4 | B6: SALARY | C6: PAY | E6: 46270 | F6: SALARY OF 1X INKLING GUARD | AC6: 28000 | AH6: 0 | AI6: =SUM(H6:AH6) -> 28000
A7: 5 | B7: SALARY | C7: PAY | E7: 46273 | F7: SALARY 2X GDS SWEET PALACE | AA7: 64000 | AH7: 0 | AI7: =SUM(H7:AH7) -> 64000
A8: 6 | B8: SALARY | C8: PAY | E8: 46273 | F8: SALARY OF 1X J SONS GD | T8: 24000 | AH8: 0 | AI8: =SUM(H8:AH8) -> 24000
A9: 7 | B9: SALARY | C9: PAY | E9: 46270 | F9: SALARY OF NOVA GD AUG AND SEP CLEARED | K9: 47000 | AH9: 0 | AI9: =SUM(H9:AH9) -> 47000
A10: 8 | B10: SALARY | C10: PAY | E10: 46274 | F10: SALARY OF RELEIVER RIAZ | AB10: 25000 | AH10: 0 | AI10: =SUM(H10:AH10) -> 25000
A11: 9 | B11: SALARY | C11: PAY | E11: 46272 | F11: SALARY OF GUL REHMAN | AH11: 55000 | AI11: =SUM(H11:AH11) -> 55000
A12: 10 | B12: SALARY | C12: PAY | E12: 46275 | F12: SALARY OF MIU CAMP OFFICE | AH12: 35000 | AI12: =SUM(H12:AH12) -> 35000
A13: 11 | B13: SALARY | C13: PAY | E13: 46275 | F13: SALARY OF 5X WUSAT GUARDS | AH13: 161747 | AI13: =SUM(H13:AH13) -> 161747
A14: 12 | B14: SALARY | C14: PAY | E14: 46275 | F14: SALARY OF DHA DENTAL GUARD | AH14: 28000 | AI14: =SUM(H14:AH14) -> 28000
A15: 13 | B15: SALARY | C15: PAY | E15: 46275 | F15: SALARY OF 4X AWT GUARDS | AD15: 91419 | AH15: 0 | AI15: =SUM(H15:AH15) -> 91419
A16: 14 | B16: SALARY | C16: PAY | E16: 46275 | F16: SALARY OF 6X DOLMEN GDS | Z16: 223000 | AH16: 0 | AI16: =SUM(H16:AH16) -> 223000 | AN16: 385774
A17: 15 | B17: SALARY | C17: PAY | E17: 46275 | F17: SALARY OF LEXUS AND MIMC | AH17: 899000 | AI17: =SUM(H17:AH17) -> 899000 | AN17: -165355
A18: 16 | B18: SALARY | C18: PAY | E18: 46276 | F18: SALARY OF 5X OFFICE STAFF | AH18: 270000 | AI18: =SUM(H18:AH18) -> 270000
A19: 17 | B19: SALARY | C19: PAY | E19: 46276 | F19: SALARY OF 3X DOLMEN GDS | Z19: 111000 | AH19: 0 | AI19: =SUM(H19:AH19) -> 111000
A20: 18 | B20: SALARY | C20: PAY | E20: 46276 | F20: SALARY OF 1X WUSAT GD | J20: 6307 | AH20: 0 | AI20: =SUM(H20:AH20) -> 6307
A21: 19 | B21: SALARY | C21: PAY | E21: 46276 | F21: SALARY OF 4X EMAAR GDS | H21: 159064 | AH21: 0 | AI21: =SUM(H21:AH21) -> 159064
A22: 20 | B22: SALARY | C22: PAY | E22: 46276 | F22: SALARY OF 1X WUSAT GD | J22: 33030 | AH22: 0 | AI22: =SUM(H22:AH22) -> 33030
A23: 21 | B23: SALARY | C23: PAY | E23: 46276 | F23: SALARY OF 103X SALARY OF HMC GUARDS | U23: 3999775 | AH23: 0 | AI23: =SUM(H23:AH23) -> 3999775
A24: 22 | B24: SALARY | C24: PAY | E24: 46279 | F24: SALARIES OF PCI | P24: 530548 | AH24: 0 | AI24: =SUM(H24:AH24) -> 530548
A25: 23 | B25: SALARY | C25: PAY | E25: 46283 | F25: SALARY OF NOVA ISB GD USMAN HAIDER | K25: 25000 | AH25: 0 | AI25: =SUM(H25:AH25) -> 25000
A26: 24 | B26: SALARY | C26: PAY | E26: 46286 | F26: PRG SALARIES | R26: 49000 | AH26: 0 | AI26: =SUM(H26:AH26) -> 49000
A27: 25 | B27: SALARY | C27: PAY | E27: 46286 | F27: MANDWAAL SALARIES | S27: 50000 | AH27: 0 | AI27: =SUM(H27:AH27) -> 50000
A28: 26 | B28: SALARY | C28: PAY | E28: 46283 | F28: SALARY OF 6X HMC GUARDS SALARY | U28: 237600 | AH28: 0 | AI28: =SUM(H28:AH28) -> 237600
A29: 27 | B29: SALARY | C29: PAY | E29: 46283 | F29: SALARY OF BISMILLAH JAN NOVA PSH | M29: 26000 | AH29: 0 | AI29: =SUM(H29:AH29) -> 26000
A30: 28 | B30: SALARY | C30: PAY | E30: 46287 | F30: SALARY OF 2X HMC GUARDS | U30: 57587 | AH30: 0 | AI30: =SUM(H30:AH30) -> 57587
A31: 29 | B31: SALARY | C31: PAY | E31: 46287 | F31: SGC SALARIES | Q31: 467258 | AH31: 0 | AI31: =SUM(H31:AH31) -> 467258
A32: 30 | B32: SALARY | C32: PAY | E32: 46294 | F32: SALARIES OF NOVA ISB | K32: 471129 | AH32: 0 | AI32: =SUM(H32:AH32) -> 471129
A33: 31 | B33: SALARY | C33: PAY | E33: 46294 | F33: SALARIES OF NOVA PSH | M33: 170000 | AH33: 0 | AI33: =SUM(H33:AH33) -> 170000
A34: 32 | B34: SALARY | C34: PAY | E34: 46294 | F34: SALARIES OF NOVA CHD | N34: 322000 | AH34: 0 | AI34: =SUM(H34:AH34) -> 322000
A35: 33 | B35: SALARY | C35: PAY | E35: 46294 | F35: SALARIES OF NOVA QTBL | L35: 100000 | AH35: 0 | AI35: =SUM(H35:AH35) -> 100000
A36: 34 | B36: SALARY | C36: PAY | E36: 46295 | F36: SALARY OF MUHAMMAD ZAMIR FTM SEP 26 | AH36: 55000 | AI36: =SUM(H36:AH36) -> 55000
A37: 35 | B37: SALARY | C37: PAY | E37: 46276 | F37: CHEQUE FOR MIU SAL | AE37: 258000 | AH37: 0 | AI37: =SUM(H37:AH37) -> 258000
A38: 36 | B38: SALARY | C38: PAY | AH38: 0 | AI38: =SUM(H38:AH38) -> 0
A39: 37 | B39: SALARY | C39: PAY | AH39: 0 | AI39: =SUM(H39:AH39) -> 0
A40: 38 | B40: SALARY | C40: PAY | AH40: 0 | AI40: =SUM(H40:AH40) -> 0
A41: 39 | B41: SALARY | C41: PAY | AH41: 0 | AI41: =SUM(H41:AH41) -> 0
A42: 40 | B42: SALARY | C42: PAY | AH42: 0 | AI42: =SUM(H42:AH42) -> 0
A43: 41 | B43: SALARY | C43: PAY | AH43: 0 | AI43: =SUM(H43:AH43) -> 0
A44: 42 | B44: SALARY | C44: PAY | AH44: 0 | AI44: =SUM(H44:AH44) -> 0
A45: 43 | B45: SALARY | C45: PAY | AH45: 0 | AI45: =SUM(H45:AH45) -> 0
A46: 44 | B46: SALARY | C46: PAY | AH46: 0 | AI46: =SUM(H46:AH46) -> 0
A47: 45 | B47: SALARY | C47: PAY | AH47: 0 | AI47: =SUM(H47:AH47) -> 0
A48: 46 | B48: SALARY | C48: PAY | AH48: 0 | AI48: =SUM(H48:AH48) -> 0
A49: 47 | B49: SALARY | C49: PAY | AH49: 0 | AI49: =SUM(H49:AH49) -> 0
A50: SALARIES PAID | H50: =SUM(H3:H49) -> 3680263 | I50: =SUM(I3:I49) -> 0 | J50: =SUM(J3:J49) -> 39337 | K50: =SUM(K3:K49) -> 543129 | L50: =SUM(L3:L49) -> 100000 | M50: =SUM(M3:M49) -> 196000 | N50: =SUM(N3:N49) -> 322000 | O50: =SUM(O3:O49) -> 0 | ... AI50: =SUM(AI3:AI49) -> 12680663
A51: 1 | B51: SALARY | C51: ADVANCE | E51: 46283 | F51: ADVANCE TO MURSALEEN KHAN NOVA CHD | N51: 10000 | AH51: 0 | AI51: =SUM(H51:AH51) -> 10000
A52: 2 | B52: SALARY | C52: ADVANCE | E52: 46292 | F52: ADVANCE TO PCI GD SARFARAZ | P52: 5000 | AH52: 0 | AI52: =SUM(H52:AH52) -> 5000
A53: 3 | B53: SALARY | C53: ADVANCE | E53: 46292 | F53: ADVANCE TO EMAARR GD NADEEM AKHTAR | H53: 5000 | AH53: 0 | AI53: =SUM(H53:AH53) -> 5000
A54: 4 | B54: SALARY | C54: ADVANCE | E54: 46292 | F54: ADVANCE TO PCI GD KASHIF RAZA | P54: 5000 | AH54: 0 | AI54: =SUM(H54:AH54) -> 5000
A55: 5 | B55: SALARY | C55: ADVANCE | E55: 46282 | F55: ADVANCE TO NASIR ALI SGC THALIAN GUARD | Q55: 5000 | AH55: 0 | AI55: =SUM(H55:AH55) -> 5000
A56: 6 | B56: SALARY | C56: ADVANCE | AH56: 0 | AI56: =SUM(H56:AH56) -> 0
A57: 7 | B57: SALARY | C57: ADVANCE | AH57: 0 | AI57: =SUM(H57:AH57) -> 0
A58: 8 | B58: SALARY | C58: ADVANCE | AH58: 0 | AI58: =SUM(H58:AH58) -> 0
A59: 9 | B59: SALARY | C59: ADVANCE | AH59: 0 | AI59: =SUM(H59:AH59) -> 0
A60: 10 | B60: SALARY | C60: ADVANCE | AH60: 0 | AI60: =SUM(H60:AH60) -> 0
A61: 11 | B61: SALARY | C61: ADVANCE | AH61: 0 | AI61: =SUM(H61:AH61) -> 0
A62: 12 | B62: SALARY | C62: ADVANCE | AH62: 0 | AI62: =SUM(H62:AH62) -> 0
A63: 13 | B63: SALARY | C63: ADVANCE | AH63: 0 | AI63: =SUM(H63:AH63) -> 0
A64: 14 | B64: SALARY | C64: ADVANCE | AH64: 0 | AI64: =SUM(H64:AH64) -> 0
A65: 15 | B65: SALARY | C65: ADVANCE | AH65: 0 | AI65: =SUM(H65:AH65) -> 0
A66: 16 | B66: SALARY | C66: ADVANCE | AH66: 0 | AI66: =SUM(H66:AH66) -> 0
A67: 17 | B67: SALARY | C67: ADVANCE | AH67: 0 | AI67: =SUM(H67:AH67) -> 0
... A69: 19 | B69: SALARY | C69: ADVANCE | AH69: 0 | AI69: =SUM(H69:AH69) -> 0
A70: 20 | B70: SALARY | C70: ADVANCE | H70: 0 | I70: 0 | J70: 0 | K70: 0 | M70: 0 | N70: 0 | O70: 0 | P70: 0 | Q70: 0 | R70: 0 | S70: 0 | T70: 0 | U70: 0 | V70: 0 | W70: 0 | X70: 0 | Y70: 0 | Z70: 0 | AA70: 0 | AB70: 0 | AH70: 0 | AI70: =SUM(H70:AH70) -> 0
A71: 21 | B71: SALARY | C71: ADVANCE | H71: 0 | I71: 0 | J71: 0 | K71: 0 | M71: 0 | N71: 0 | O71: 0 | P71: 0 | Q71: 0 | R71: 0 | S71: 0 | T71: 0 | U71: 0 | V71: 0 | W71: 0 | X71: 0 | Y71: 0 | Z71: 0 | AA71: 0 | AB71: 0 | AH71: 0 | AI71: =SUM(H71:AH71) -> 0
A72: 22 | B72: SALARY | C72: ADVANCE | H72: 0 | I72: 0 | J72: 0 | K72: 0 | M72: 0 | N72: 0 | O72: 0 | P72: 0 | Q72: 0 | R72: 0 | S72: 0 | T72: 0 | U72: 0 | V72: 0 | W72: 0 | X72: 0 | Y72: 0 | Z72: 0 | AA72: 0 | AB72: 0 | AH72: 0 | AI72: =SUM(H72:AH72) -> 0
A73: 23 | B73: SALARY | C73: ADVANCE | H73: 0 | I73: 0 | J73: 0 | K73: 0 | M73: 0 | N73: 0 | O73: 0 | P73: 0 | Q73: 0 | R73: 0 | S73: 0 | T73: 0 | U73: 0 | V73: 0 | W73: 0 | X73: 0 | Y73: 0 | Z73: 0 | AA73: 0 | AB73: 0 | AH73: 0 | AI73: =SUM(H73:AH73) -> 0
A74: 24 | B74: SALARY | C74: ADVANCE | H74: 0 | I74: 0 | J74: 0 | K74: 0 | M74: 0 | N74: 0 | O74: 0 | P74: 0 | Q74: 0 | R74: 0 | S74: 0 | T74: 0 | U74: 0 | V74: 0 | W74: 0 | X74: 0 | Y74: 0 | Z74: 0 | AA74: 0 | AB74: 0 | AH74: 0 | AI74: =SUM(H74:AH74) -> 0
A75: 25 | B75: SALARY | C75: ADVANCE | H75: 0 | I75: 0 | J75: 0 | K75: 0 | M75: 0 | N75: 0 | O75: 0 | P75: 0 | Q75: 0 | R75: 0 | S75: 0 | T75: 0 | U75: 0 | V75: 0 | W75: 0 | X75: 0 | Y75: 0 | Z75: 0 | AA75: 0 | AB75: 0 | AH75: 0 | AI75: =SUM(H75:AH75) -> 0
A76: 26 | B76: SALARY | C76: ADVANCE | H76: 0 | I76: 0 | J76: 0 | K76: 0 | M76: 0 | N76: 0 | O76: 0 | P76: 0 | Q76: 0 | R76: 0 | S76: 0 | T76: 0 | U76: 0 | V76: 0 | W76: 0 | X76: 0 | Y76: 0 | Z76: 0 | AA76: 0 | AB76: 0 | AH76: 0 | AI76: =SUM(H76:AH76) -> 0
A77: TOTAL ADVANCE PAYMENT | H77: =SUM(H51:H76) -> 5000 | I77: =SUM(I51:I76) -> 0 | J77: =SUM(J51:J76) -> 0 | K77: =SUM(K51:K76) -> 0 | L77: =SUM(L51:L76) -> 0 | M77: =SUM(M51:M76) -> 0 | N77: =SUM(N51:N76) -> 10000 | O77: =SUM(O51:O76) -> 0 | ... AI77: =SUM(AI51:AI76) -> 30000
A78: 1 | B78: PAY | C78: DISTRIBUTION EXPENSE (PAY) | Z78: 0 | AF78: 0 | AG78: 0 | AI78: =SUM(H78:AH78) -> 0
A79: EXPENSE INCURRED ON SALARIES DISTRIBUTION | H79: =SUM(H78:H78) -> 0 | I79: =SUM(I78:I78) -> 0 | J79: =SUM(J78:J78) -> 0 | K79: =SUM(K78:K78) -> 0 | L79: =SUM(L78:L78) -> 0 | M79: =SUM(M78:M78) -> 0 | N79: =SUM(N78:N78) -> 0 | O79: =SUM(O78:O78) -> 0 | ... AI79: =SUM(AI78:AI78) -> 0
A80: 1 | B80: PETTY EXPENSES | C80: TRAVEL EXPENSES | E80: 46295 | F80: FUEL ALLOWANCES FTM SEP AND OCT 26 | AH80: 75000 | AI80: =SUM(H80:AH80) -> 75000 | AN80: =AI79+AI140+AI156+AI160+AI164+AI176+AI184+AI191 -> 1581988
A81: 2 | B81: PETTY EXPENSES | C81: TRAVEL EXPENSES | E81: 01 Sept 2026 | F81: Fuel expenses excess of fuel card | AH81: 8313 | AI81: =SUM(H81:AH81) -> 8313
A82: 3 | B82: PETTY EXPENSES | C82: TRAVEL EXPENSES | E82: 01 Sept 2026 | F82: HMC invoice courier charges | U82: 500 | AH82: 0 | AI82: =SUM(H82:AH82) -> 500
A83: 4 | B83: PETTY EXPENSES | C83: TRAVEL EXPENSES | E83: 03 Sept 2026 | F83: GGS-PCI-GGS Visit by Gul Rehman for meeting with Col Arshad. | P83: 188 | AH83: 0 | AI83: =SUM(H83:AH83) -> 188
A84: 5 | B84: PETTY EXPENSES | C84: TRAVEL EXPENSES | E84: 03 Sept 2026 | F84: August 2026 invoice submitted to Dolmen, Karachi | Z84: 400 | AH84: 0 | AI84: =SUM(H84:AH84) -> 400
A85: 6 | B85: PETTY EXPENSES | C85: TRAVEL EXPENSES | E85: 10 Sept 2026 | F85: Dispatched Sim (0333-1148102) to Mr Roshan Khan | AE85: 500 | AH85: 0 | AI85: =SUM(H85:AH85) -> 500
A86: 7 | B86: PETTY EXPENSES | C86: TRAVEL EXPENSES | E86: 10 Sept 2026 | F86: Dispatched Termination Letter to Supv Ikhlaq Iqbal, HMC, Taxila | U86: 300 | AH86: 0 | AI86: =SUM(H86:AH86) -> 300
A87: 8 | B87: PETTY EXPENSES | C87: TRAVEL EXPENSES | E87: 10 Sept 2026 | F87: Dispatched Profile to Mr Roshan Khan, MZD | AE87: 350 | AH87: 0 | AI87: =SUM(H87:AH87) -> 350
A88: 9 | B88: PETTY EXPENSES | C88: TRAVEL EXPENSES | E88: 10 Sept 2026 | F88: To Drop & Pick Reliever (Inklings) | AC88: 400 | AH88: 0 | AI88: =SUM(H88:AH88) -> 400
A89: 10 | B89: PETTY EXPENSES | C89: TRAVEL EXPENSES | E89: 12 Sept 2026 | F89: Fuel in Office Bike | AH89: 760 | AI89: =SUM(H89:AH89) -> 760
A90: 11 | B90: PETTY EXPENSES | C90: TRAVEL EXPENSES | E90: 14 Sept 2026 | F90: Fuel in Office Bike for visits to EMAAR & AWT (Card Limit Exceeded) | AH90: 750 | AI90: =SUM(H90:AH90) -> 750
A91: 12 | B91: PETTY EXPENSES | C91: TRAVEL EXPENSES | E91: 15 Sept 2026 | F91: Fuel charges claimed by Supv Kashif Raza for 3 x visits to Zee Cambridge School, Gulraiz | AF91: 520 | AH91: 0 | AI91: =SUM(H91:AH91) -> 520
A92: 13 | B92: PETTY EXPENSES | C92: TRAVEL EXPENSES | E92: 16 Sept 2026 | F92: Fuel Charges (GGS-EMAAR-GGS) / Meeting with the CEO | H92: 220 | AH92: 0 | AI92: =SUM(H92:AH92) -> 220
A93: 14 | B93: PETTY EXPENSES | C93: TRAVEL EXPENSES | E93: 19 Sept 2026 | F93: Fuel charges claimed by Reli Riaz for August 2026 (multiple sites of ISB/RWP) | AH93: 5350 | AI93: =SUM(H93:AH93) -> 5350
A94: 15 | B94: PETTY EXPENSES | C94: TRAVEL EXPENSES | E94: 22 Sept 2026 | F94: 2 x visits by Supv Said Maroof (University Town to Home Department, Civ Secretariat) - KP NOC | AH94: 600 | AI94: =SUM(H94:AH94) -> 600
A95: 16 | B95: PETTY EXPENSES | C95: TRAVEL EXPENSES | AH95: 0 | AI95: =SUM(H95:AH95) -> 0
A96: 17 | B96: PETTY EXPENSES | C96: TRAVEL EXPENSES | AH96: 0 | AI96: =SUM(H96:AH96) -> 0
A97: 18 | B97: PETTY EXPENSES | C97: TRAVEL EXPENSES | AH97: 0 | AI97: =SUM(H97:AH97) -> 0
A98: 19 | B98: PETTY EXPENSES | C98: TRAVEL EXPENSES | AH98: 0 | AI98: =SUM(H98:AH98) -> 0
A99: 20 | B99: PETTY EXPENSES | C99: TRAVEL EXPENSES | AH99: 0 | AI99: =SUM(H99:AH99) -> 0
A100: 21 | B100: PETTY EXPENSES | C100: TRAVEL EXPENSES | AH100: 0 | AI100: =SUM(H100:AH100) -> 0
A101: 22 | B101: PETTY EXPENSES | C101: TRAVEL EXPENSES | AH101: 0 | AI101: =SUM(H101:AH101) -> 0
...

Sheet P&L
B2: PROFIT AND LOSS STATEMENT
B3: Revenue | G3: ='INCOME WITHDRWAL STATE'!F36 -> 16378009 | J3: MIU INCLUDED
B4: Expenses
B5: SALARIES PAID | E5: ='SUMMARY PAY EXPENSE SHEET'!AD3 -> 12680663
B6: TOTAL ADVANCE PAYMENT | E6: ='SUMMARY PAY EXPENSE SHEET'!AD4 -> 30000
B7: EXPENSE INCURRED ON SALARIES DISTRIBUTION | E7: ='SUMMARY PAY EXPENSE SHEET'!AD5 -> 0
B8: TOTAL TRAVEL EXPENSE | E8: ='SUMMARY PAY EXPENSE SHEET'!AD6 -> 94151
B9: TOTAL FOOD EXPENSE | E9: ='SUMMARY PAY EXPENSE SHEET'!AD7 -> 10830
B10: TOTAL TEABREAK EXPENSE | E10: ='SUMMARY PAY EXPENSE SHEET'!AD8 -> 7680
B11: TOTAL STATIONERY EXPENSE | E11: ='SUMMARY PAY EXPENSE SHEET'!AD9 -> 0
B12: TOTAL RENT UTILITIES & INTERNET EXPENSE | E12: ='SUMMARY PAY EXPENSE SHEET'!AD10 -> 657745
B13: TOTAL INVENTORY EXPENSE | E13: ='SUMMARY PAY EXPENSE SHEET'!AD11 -> 292750
B14: TOTAL LEGAL EXPENSE | E14: ='SUMMARY PAY EXPENSE SHEET'!AD12 -> 518832 | L14: 1678890
B15: TOTAL MISCELLENIOUS EXPENSE | E15: ='SUMMARY PAY EXPENSE SHEET'!AD13 -> 96902 | L15: =L14-102550 -> 1576340 | O15: 1523828 | Q15: =L15-O15 -> 52512
B16: TOTAL DRAWINGS BY CEO / CFO | E16: ='SUMMARY PAY EXPENSE SHEET'!AD14 -> 197410
B17: TOTAL EXPENSES | E17: =SUM(E5:F16) -> 14586963
B18: PROFIT /LOSS | H18: =G3-E17 -> 1791046 | L18: =G3-L15-E5 -> 2121006 | O18: 2185314 | Q18: =L18-O18 -> -64308
L19: =L18*0.25 -> 530251.5
